tilesetgenerator
